MDANSE/__init__.py
MDANSE/Chemistry/ChemicalSystem.py
MDANSE/Chemistry/Databases.py
MDANSE/Chemistry/__init__.py
MDANSE/Chemistry/atoms.json
MDANSE/Chemistry/neutron_scattering_lengths_nist.csv
MDANSE/Core/Error.py
MDANSE/Core/Platform.py
MDANSE/Core/Singleton.py
MDANSE/Core/SubclassFactory.py
MDANSE/Core/__init__.py
MDANSE/Framework/Configurable.py
MDANSE/Framework/Status.py
MDANSE/Framework/Units.py
MDANSE/Framework/__init__.py
MDANSE/Framework/units.json
MDANSE/Framework/AtomGrouping/grouping.py
MDANSE/Framework/AtomMapping/__init__.py
MDANSE/Framework/AtomMapping/atom_mapping.py
MDANSE/Framework/AtomSelector/__init__.py
MDANSE/Framework/AtomSelector/atom_selection.py
MDANSE/Framework/AtomSelector/general_selection.py
MDANSE/Framework/AtomSelector/group_selection.py
MDANSE/Framework/AtomSelector/molecule_selection.py
MDANSE/Framework/AtomSelector/selector.py
MDANSE/Framework/AtomSelector/spatial_selection.py
MDANSE/Framework/Configurators/ASEFileConfigurator.py
MDANSE/Framework/Configurators/AseInputFileConfigurator.py
MDANSE/Framework/Configurators/AtomMappingConfigurator.py
MDANSE/Framework/Configurators/AtomSelectionConfigurator.py
MDANSE/Framework/Configurators/AtomTransmutationConfigurator.py
MDANSE/Framework/Configurators/AxisSelectionConfigurator.py
MDANSE/Framework/Configurators/BooleanConfigurator.py
MDANSE/Framework/Configurators/ConfigFileConfigurator.py
MDANSE/Framework/Configurators/CorrelationFramesConfigurator.py
MDANSE/Framework/Configurators/DerivativeOrderConfigurator.py
MDANSE/Framework/Configurators/DistHistCutoffConfigurator.py
MDANSE/Framework/Configurators/FieldFileConfigurator.py
MDANSE/Framework/Configurators/FileWithAtomDataConfigurator.py
MDANSE/Framework/Configurators/FloatConfigurator.py
MDANSE/Framework/Configurators/FramesConfigurator.py
MDANSE/Framework/Configurators/GroupingLevelConfigurator.py
MDANSE/Framework/Configurators/HDFInputFileConfigurator.py
MDANSE/Framework/Configurators/HDFTrajectoryConfigurator.py
mdanse-2.0.0rc2.dist-info/licenses/AUTHORS
mdanse-2.0.0rc2.dist-info/licenses/LICENSE
mdanse-2.0.0rc2.dist-info/METADATA
mdanse-2.0.0rc2.dist-info/WHEEL
mdanse-2.0.0rc2.dist-info/entry_points.txt
mdanse-2.0.0rc2.dist-info/top_level.txt
mdanse-2.0.0rc2.dist-info/RECORD
